{
 "fragments": [
  {
   "begin": "0.000",
   "children": [],
   "end": "0.400",
   "id": "f000001",
   "language": "eng",
   "lines": [
    "One"
   ]
  },
  {
   "begin": "0.400",
   "children": [],
   "end": "0.800",
   "id": "f000002",
   "language": "eng",
   "lines": [
    "character"
   ]
  },
  {
   "begin": "0.800",
   "children": [],
   "end": "0.840",
   "id": "f000003",
   "language": "eng",
   "lines": [
    "in"
   ]
  },
  {
   "begin": "0.840",
   "children": [],
   "end": "1.440",
   "id": "f000004",
   "language": "eng",
   "lines": [
    "this"
   ]
  },
  {
   "begin": "1.440",
   "children": [],
   "end": "1.840",
   "id": "f000005",
   "language": "eng",
   "lines": [
    "work"
   ]
  },
  {
   "begin": "1.840",
   "children": [],
   "end": "2.160",
   "id": "f000006",
   "language": "eng",
   "lines": [
    "passed"
   ]
  },
  {
   "begin": "2.160",
   "children": [],
   "end": "2.480",
   "id": "f000007",
   "language": "eng",
   "lines": [
    "through"
   ]
  },
  {
   "begin": "2.480",
   "children": [],
   "end": "2.880",
   "id": "f000008",
   "language": "eng",
   "lines": [
    "five"
   ]
  },
  {
   "begin": "2.880",
   "children": [],
   "end": "3.120",
   "id": "f000009",
   "language": "eng",
   "lines": [
    "keeps"
   ]
  },
  {
   "begin": "3.120",
   "children": [],
   "end": "3.200",
   "id": "f000010",
   "language": "eng",
   "lines": [
    "and"
   ]
  },
  {
   "begin": "3.200",
   "children": [],
   "end": "3.800",
   "id": "f000011",
   "language": "eng",
   "lines": [
    "slew"
   ]
  },
  {
   "begin": "3.800",
   "children": [],
   "end": "4.160",
   "id": "f000012",
   "language": "eng",
   "lines": [
    "six"
   ]
  },
  {
   "begin": "4.160",
   "children": [],
   "end": "5.000",
   "id": "f000013",
   "language": "eng",
   "lines": [
    "generals"
   ]
  },
  {
   "begin": "5.000",
   "children": [],
   "end": "5.160",
   "id": "f000014",
   "language": "eng",
   "lines": [
    "in"
   ]
  },
  {
   "begin": "5.160",
   "children": [],
   "end": "5.440",
   "id": "f000015",
   "language": "eng",
   "lines": [
    "order"
   ]
  },
  {
   "begin": "5.440",
   "children": [],
   "end": "5.680",
   "id": "f000016",
   "language": "eng",
   "lines": [
    "to"
   ]
  },
  {
   "begin": "5.680",
   "children": [],
   "end": "6.040",
   "id": "f000017",
   "language": "eng",
   "lines": [
    "return"
   ]
  },
  {
   "begin": "6.040",
   "children": [],
   "end": "6.880",
   "id": "f000018",
   "language": "eng",
   "lines": [
    "to"
   ]
  },
  {
   "begin": "6.880",
   "children": [],
   "end": "7.280",
   "id": "f000019",
   "language": "eng",
   "lines": [
    "his"
   ]
  },
  {
   "begin": "7.280",
   "children": [],
   "end": "7.520",
   "id": "f000020",
   "language": "eng",
   "lines": [
    "liege"
   ]
  },
  {
   "begin": "7.520",
   "children": [],
   "end": "7.760",
   "id": "f000021",
   "language": "eng",
   "lines": [
    "while"
   ]
  },
  {
   "begin": "7.760",
   "children": [],
   "end": "8.400",
   "id": "f000022",
   "language": "eng",
   "lines": [
    "escaping"
   ]
  },
  {
   "begin": "8.400",
   "children": [],
   "end": "8.800",
   "id": "f000023",
   "language": "eng",
   "lines": [
    "from"
   ]
  },
  {
   "begin": "8.800",
   "children": [],
   "end": "8.840",
   "id": "f000024",
   "language": "eng",
   "lines": [
    "an"
   ]
  },
  {
   "begin": "8.840",
   "children": [],
   "end": "9.320",
   "id": "f000025",
   "language": "eng",
   "lines": [
    "opposing"
   ]
  },
  {
   "begin": "9.320",
   "children": [],
   "end": "9.920",
   "id": "f000026",
   "language": "eng",
   "lines": [
    "commander"
   ]
  },
  {
   "begin": "9.920",
   "children": [],
   "end": "10.080",
   "id": "f000027",
   "language": "eng",
   "lines": [
    "who"
   ]
  },
  {
   "begin": "10.080",
   "children": [],
   "end": "10.280",
   "id": "f000028",
   "language": "eng",
   "lines": [
    "had"
   ]
  },
  {
   "begin": "10.280",
   "children": [],
   "end": "10.520",
   "id": "f000029",
   "language": "eng",
   "lines": [
    "gifted"
   ]
  },
  {
   "begin": "10.520",
   "children": [],
   "end": "10.520",
   "id": "f000030",
   "language": "eng",
   "lines": [
    "him"
   ]
  },
  {
   "begin": "10.520",
   "children": [],
   "end": "10.920",
   "id": "f000031",
   "language": "eng",
   "lines": [
    "the"
   ]
  },
  {
   "begin": "10.920",
   "children": [],
   "end": "11.240",
   "id": "f000032",
   "language": "eng",
   "lines": [
    "Red"
   ]
  },
  {
   "begin": "11.240",
   "children": [],
   "end": "11.560",
   "id": "f000033",
   "language": "eng",
   "lines": [
    "Hare"
   ]
  },
  {
   "begin": "11.560",
   "children": [],
   "end": "12.200",
   "id": "f000034",
   "language": "eng",
   "lines": [
    "horse"
   ]
  },
  {
   "begin": "12.200",
   "children": [],
   "end": "12.520",
   "id": "f000035",
   "language": "eng",
   "lines": [
    "in"
   ]
  },
  {
   "begin": "12.520",
   "children": [],
   "end": "12.520",
   "id": "f000036",
   "language": "eng",
   "lines": [
    "order"
   ]
  },
  {
   "begin": "12.520",
   "children": [],
   "end": "13.440",
   "id": "f000037",
   "language": "eng",
   "lines": [
    "to"
   ]
  },
  {
   "begin": "13.440",
   "children": [],
   "end": "13.840",
   "id": "f000038",
   "language": "eng",
   "lines": [
    "sway"
   ]
  },
  {
   "begin": "13.840",
   "children": [],
   "end": "14.160",
   "id": "f000039",
   "language": "eng",
   "lines": [
    "his"
   ]
  },
  {
   "begin": "14.160",
   "children": [],
   "end": "15.400",
   "id": "f000040",
   "language": "eng",
   "lines": [
    "allegiances."
   ]
  },
  {
   "begin": "15.400",
   "children": [],
   "end": "15.480",
   "id": "f000041",
   "language": "eng",
   "lines": [
    "A"
   ]
  },
  {
   "begin": "15.480",
   "children": [],
   "end": "16.280",
   "id": "f000042",
   "language": "eng",
   "lines": [
    "commander"
   ]
  },
  {
   "begin": "16.280",
   "children": [],
   "end": "16.280",
   "id": "f000043",
   "language": "eng",
   "lines": [
    "in"
   ]
  },
  {
   "begin": "16.280",
   "children": [],
   "end": "16.560",
   "id": "f000044",
   "language": "eng",
   "lines": [
    "this"
   ]
  },
  {
   "begin": "16.560",
   "children": [],
   "end": "16.880",
   "id": "f000045",
   "language": "eng",
   "lines": [
    "work"
   ]
  },
  {
   "begin": "16.880",
   "children": [],
   "end": "17.080",
   "id": "f000046",
   "language": "eng",
   "lines": [
    "is"
   ]
  },
  {
   "begin": "17.080",
   "children": [],
   "end": "17.440",
   "id": "f000047",
   "language": "eng",
   "lines": [
    "tricked"
   ]
  },
  {
   "begin": "17.440",
   "children": [],
   "end": "17.680",
   "id": "f000048",
   "language": "eng",
   "lines": [
    "into"
   ]
  },
  {
   "begin": "17.680",
   "children": [],
   "end": "18.360",
   "id": "f000049",
   "language": "eng",
   "lines": [
    "chain"
   ]
  },
  {
   "begin": "18.360",
   "children": [],
   "end": "18.880",
   "id": "f000050",
   "language": "eng",
   "lines": [
    "linking"
   ]
  },
  {
   "begin": "18.880",
   "children": [],
   "end": "18.880",
   "id": "f000051",
   "language": "eng",
   "lines": [
    "his"
   ]
  },
  {
   "begin": "18.880",
   "children": [],
   "end": "18.880",
   "id": "f000052",
   "language": "eng",
   "lines": [
    "ships"
   ]
  },
  {
   "begin": "18.880",
   "children": [],
   "end": "19.640",
   "id": "f000053",
   "language": "eng",
   "lines": [
    "together,"
   ]
  },
  {
   "begin": "19.640",
   "children": [],
   "end": "20.880",
   "id": "f000054",
   "language": "eng",
   "lines": [
    "causing"
   ]
  },
  {
   "begin": "20.880",
   "children": [],
   "end": "20.880",
   "id": "f000055",
   "language": "eng",
   "lines": [
    "him"
   ]
  },
  {
   "begin": "20.880",
   "children": [],
   "end": "21.280",
   "id": "f000056",
   "language": "eng",
   "lines": [
    "to"
   ]
  },
  {
   "begin": "21.280",
   "children": [],
   "end": "21.640",
   "id": "f000057",
   "language": "eng",
   "lines": [
    "suffer"
   ]
  },
  {
   "begin": "21.640",
   "children": [],
   "end": "22.040",
   "id": "f000058",
   "language": "eng",
   "lines": [
    "an"
   ]
  },
  {
   "begin": "22.040",
   "children": [],
   "end": "22.160",
   "id": "f000059",
   "language": "eng",
   "lines": [
    "epic"
   ]
  },
  {
   "begin": "22.160",
   "children": [],
   "end": "22.680",
   "id": "f000060",
   "language": "eng",
   "lines": [
    "defeat"
   ]
  },
  {
   "begin": "22.680",
   "children": [],
   "end": "22.800",
   "id": "f000061",
   "language": "eng",
   "lines": [
    "at"
   ]
  },
  {
   "begin": "22.800",
   "children": [],
   "end": "23.000",
   "id": "f000062",
   "language": "eng",
   "lines": [
    "the"
   ]
  },
  {
   "begin": "23.000",
   "children": [],
   "end": "23.440",
   "id": "f000063",
   "language": "eng",
   "lines": [
    "battle"
   ]
  },
  {
   "begin": "23.440",
   "children": [],
   "end": "23.800",
   "id": "f000064",
   "language": "eng",
   "lines": [
    "of"
   ]
  },
  {
   "begin": "23.800",
   "children": [],
   "end": "24.000",
   "id": "f000065",
   "language": "eng",
   "lines": [
    "Red"
   ]
  },
  {
   "begin": "24.000",
   "children": [],
   "end": "25.120",
   "id": "f000066",
   "language": "eng",
   "lines": [
    "Cliffs."
   ]
  },
  {
   "begin": "25.120",
   "children": [],
   "end": "25.320",
   "id": "f000067",
   "language": "eng",
   "lines": [
    "In"
   ]
  },
  {
   "begin": "25.320",
   "children": [],
   "end": "25.600",
   "id": "f000068",
   "language": "eng",
   "lines": [
    "this"
   ]
  },
  {
   "begin": "25.600",
   "children": [],
   "end": "26.120",
   "id": "f000069",
   "language": "eng",
   "lines": [
    "novel,"
   ]
  },
  {
   "begin": "26.120",
   "children": [],
   "end": "26.800",
   "id": "f000070",
   "language": "eng",
   "lines": [
    "Cao"
   ]
  },
  {
   "begin": "26.800",
   "children": [],
   "end": "27.320",
   "id": "f000071",
   "language": "eng",
   "lines": [
    "Cao"
   ]
  },
  {
   "begin": "27.320",
   "children": [],
   "end": "28.000",
   "id": "f000072",
   "language": "eng",
   "lines": [
    "(\"t'sao"
   ]
  },
  {
   "begin": "28.000",
   "children": [],
   "end": "28.920",
   "id": "f000073",
   "language": "eng",
   "lines": [
    "t'sao\")"
   ]
  },
  {
   "begin": "28.920",
   "children": [],
   "end": "29.480",
   "id": "f000074",
   "language": "eng",
   "lines": [
    "narrowly"
   ]
  },
  {
   "begin": "29.480",
   "children": [],
   "end": "30.040",
   "id": "f000075",
   "language": "eng",
   "lines": [
    "escapes"
   ]
  },
  {
   "begin": "30.040",
   "children": [],
   "end": "30.160",
   "id": "f000076",
   "language": "eng",
   "lines": [
    "with"
   ]
  },
  {
   "begin": "30.160",
   "children": [],
   "end": "30.440",
   "id": "f000077",
   "language": "eng",
   "lines": [
    "his"
   ]
  },
  {
   "begin": "30.440",
   "children": [],
   "end": "30.840",
   "id": "f000078",
   "language": "eng",
   "lines": [
    "life"
   ]
  },
  {
   "begin": "30.840",
   "children": [],
   "end": "30.840",
   "id": "f000079",
   "language": "eng",
   "lines": [
    "due"
   ]
  },
  {
   "begin": "30.840",
   "children": [],
   "end": "30.880",
   "id": "f000080",
   "language": "eng",
   "lines": [
    "to"
   ]
  },
  {
   "begin": "30.880",
   "children": [],
   "end": "31.240",
   "id": "f000081",
   "language": "eng",
   "lines": [
    "the"
   ]
  },
  {
   "begin": "31.240",
   "children": [],
   "end": "31.760",
   "id": "f000082",
   "language": "eng",
   "lines": [
    "mercy"
   ]
  },
  {
   "begin": "31.760",
   "children": [],
   "end": "31.840",
   "id": "f000083",
   "language": "eng",
   "lines": [
    "of"
   ]
  },
  {
   "begin": "31.840",
   "children": [],
   "end": "33.440",
   "id": "f000084",
   "language": "eng",
   "lines": [
    "Guan"
   ]
  },
  {
   "begin": "33.440",
   "children": [],
   "end": "33.800",
   "id": "f000085",
   "language": "eng",
   "lines": [
    "Yu,"
   ]
  },
  {
   "begin": "33.800",
   "children": [],
   "end": "34.680",
   "id": "f000086",
   "language": "eng",
   "lines": [
    "whom"
   ]
  },
  {
   "begin": "34.680",
   "children": [],
   "end": "34.680",
   "id": "f000087",
   "language": "eng",
   "lines": [
    "he"
   ]
  },
  {
   "begin": "34.680",
   "children": [],
   "end": "34.680",
   "id": "f000088",
   "language": "eng",
   "lines": [
    "had"
   ]
  },
  {
   "begin": "34.680",
   "children": [],
   "end": "35.120",
   "id": "f000089",
   "language": "eng",
   "lines": [
    "earlier"
   ]
  },
  {
   "begin": "35.120",
   "children": [],
   "end": "35.200",
   "id": "f000090",
   "language": "eng",
   "lines": [
    "recruited."
   ]
  },
  {
   "begin": "35.200",
   "children": [],
   "end": "35.840",
   "id": "f000091",
   "language": "eng",
   "lines": [
    "For"
   ]
  },
  {
   "begin": "35.840",
   "children": [],
   "end": "36.200",
   "id": "f000092",
   "language": "eng",
   "lines": [
    "10"
   ]
  },
  {
   "begin": "36.200",
   "children": [],
   "end": "36.880",
   "id": "f000093",
   "language": "eng",
   "lines": [
    "points,"
   ]
  },
  {
   "begin": "36.880",
   "children": [],
   "end": "37.280",
   "id": "f000094",
   "language": "eng",
   "lines": [
    "the"
   ]
  },
  {
   "begin": "37.280",
   "children": [],
   "end": "37.880",
   "id": "f000095",
   "language": "eng",
   "lines": [
    "conflict"
   ]
  },
  {
   "begin": "37.880",
   "children": [],
   "end": "38.000",
   "id": "f000096",
   "language": "eng",
   "lines": [
    "between"
   ]
  },
  {
   "begin": "38.000",
   "children": [],
   "end": "38.760",
   "id": "f000097",
   "language": "eng",
   "lines": [
    "states"
   ]
  },
  {
   "begin": "38.760",
   "children": [],
   "end": "39.080",
   "id": "f000098",
   "language": "eng",
   "lines": [
    "such"
   ]
  },
  {
   "begin": "39.080",
   "children": [],
   "end": "39.280",
   "id": "f000099",
   "language": "eng",
   "lines": [
    "as"
   ]
  },
  {
   "begin": "39.280",
   "children": [],
   "end": "39.680",
   "id": "f000100",
   "language": "eng",
   "lines": [
    "Wei"
   ]
  },
  {
   "begin": "39.680",
   "children": [],
   "end": "39.720",
   "id": "f000101",
   "language": "eng",
   "lines": [
    "and"
   ]
  },
  {
   "begin": "39.720",
   "children": [],
   "end": "40.280",
   "id": "f000102",
   "language": "eng",
   "lines": [
    "Shu"
   ]
  },
  {
   "begin": "40.280",
   "children": [],
   "end": "40.920",
   "id": "f000103",
   "language": "eng",
   "lines": [
    "appears"
   ]
  },
  {
   "begin": "40.920",
   "children": [],
   "end": "40.960",
   "id": "f000104",
   "language": "eng",
   "lines": [
    "in"
   ]
  },
  {
   "begin": "40.960",
   "children": [],
   "end": "41.280",
   "id": "f000105",
   "language": "eng",
   "lines": [
    "what"
   ]
  },
  {
   "begin": "41.280",
   "children": [],
   "end": "41.480",
   "id": "f000106",
   "language": "eng",
   "lines": [
    "novel"
   ]
  },
  {
   "begin": "41.480",
   "children": [],
   "end": "41.640",
   "id": "f000107",
   "language": "eng",
   "lines": [
    "that"
   ]
  },
  {
   "begin": "41.640",
   "children": [],
   "end": "42.640",
   "id": "f000108",
   "language": "eng",
   "lines": [
    "dramatizes"
   ]
  },
  {
   "begin": "42.640",
   "children": [],
   "end": "42.640",
   "id": "f000109",
   "language": "eng",
   "lines": [
    "a"
   ]
  },
  {
   "begin": "42.640",
   "children": [],
   "end": "43.080",
   "id": "f000110",
   "language": "eng",
   "lines": [
    "period"
   ]
  },
  {
   "begin": "43.080",
   "children": [],
   "end": "43.400",
   "id": "f000111",
   "language": "eng",
   "lines": [
    "of"
   ]
  },
  {
   "begin": "43.400",
   "children": [],
   "end": "44.760",
   "id": "f000112",
   "language": "eng",
   "lines": [
    "Chinese"
   ]
  },
  {
   "begin": "44.760",
   "children": [],
   "end": "45.200",
   "id": "f000113",
   "language": "eng",
   "lines": [
    "history"
   ]
  },
  {
   "begin": "45.200",
   "children": [],
   "end": "45.400",
   "id": "f000114",
   "language": "eng",
   "lines": [
    "after"
   ]
  },
  {
   "begin": "45.400",
   "children": [],
   "end": "45.640",
   "id": "f000115",
   "language": "eng",
   "lines": [
    "the"
   ]
  },
  {
   "begin": "45.640",
   "children": [],
   "end": "46.040",
   "id": "f000116",
   "language": "eng",
   "lines": [
    "Han"
   ]
  },
  {
   "begin": "46.040",
   "children": [],
   "end": "47.160",
   "id": "f000117",
   "language": "eng",
   "lines": [
    "dynasty?"
   ]
  }
 ]
}